JokeMachine/JokeMachine.py
JokeMachine/__init__.py
JokeMachine-0.0.1.dist-info/LICENSE
JokeMachine-0.0.1.dist-info/METADATA
JokeMachine-0.0.1.dist-info/WHEEL
JokeMachine-0.0.1.dist-info/top_level.txt
JokeMachine-0.0.1.dist-info/RECORD
