Metadata-Version: 2.1
Name: JokeMachine
Version: 0.0.1
Summary: A library to fetch dad jokes from a list of 3000 jokes.
Author: Sarah Akers
Author-email: Ripsweetener@gmail.com
Keywords: joke,dad joke,humor,funny
Classifier: Development Status :: 5 - Production/Stable
Classifier: Intended Audience :: Developers
Classifier: License :: OSI Approved :: MIT License
Classifier: Programming Language :: Python :: 3
Classifier: Programming Language :: Python :: 3.6
Classifier: Programming Language :: Python :: 3.7
Classifier: Programming Language :: Python :: 3.8
Classifier: Programming Language :: Python :: 3.9
Requires-Python: >=3.6
License-File: LICENSE
Requires-Dist: requests
